BasicCal/__init__.py
BasicCal/basicCal.py
basicCal-1.0.dist-info/METADATA
basicCal-1.0.dist-info/WHEEL
basicCal-1.0.dist-info/top_level.txt
basicCal-1.0.dist-info/RECORD
