Metadata-Version: 2.1
Name: basicCal
Version: 1.0
Summary: Basic Math Functions
Home-page: UNKNOWN
Author: Zach Russell
Author-email: UNKNOWN
License: UNKNOWN
Platform: UNKNOWN
